{
  "version": "v4",
  "repo": "borisyankov/DefinitelyTyped",
  "ref": "master",
  "path": "typings",
  "bundle": "typings/tsd.d.ts",
  "installed": {
    "node/node.d.ts": {
      "commit": "24c59ec02110c942fcdf453ecdc13babca2b2205"
    },
    "mocha/mocha.d.ts": {
      "commit": "138ad74b9e8e6c08af7633964962835add4c91e2"
    },
    "assertion-error/assertion-error.d.ts": {
      "commit": "138ad74b9e8e6c08af7633964962835add4c91e2"
    },
    "chai/chai.d.ts": {
      "commit": "138ad74b9e8e6c08af7633964962835add4c91e2"
    }
  }
}
